openai_responses_server/__init__.py
openai_responses_server/cli.py
openai_responses_server/server.py
openai_responses_server/version.py
openai_responses_server-0.2.7.dist-info/licenses/LICENSE
openai_responses_server-0.2.7.dist-info/METADATA
openai_responses_server-0.2.7.dist-info/WHEEL
openai_responses_server-0.2.7.dist-info/entry_points.txt
openai_responses_server-0.2.7.dist-info/top_level.txt
openai_responses_server-0.2.7.dist-info/RECORD
